LICENSE
MANIFEST.in
README.md
setup.cfg
setup.py
certbot_route53/__init__.py
certbot_route53.egg-info/PKG-INFO
certbot_route53.egg-info/SOURCES.txt
certbot_route53.egg-info/dependency_links.txt
certbot_route53.egg-info/requires.txt
certbot_route53.egg-info/top_level.txt