Metadata-Version: 1.1
Name: certbot-route53
Version: 0.2.0
Summary: Route53 plugin for certbot
Home-page: https://github.com/lifeonmarspt/certbot-route53
Author: Hugo Peixoto
Author-email: hugo@lifeonmars.pt
License: Apache2.0
Keywords: certbot,route53,aws
Platform: UNKNOWN
Classifier: Development Status :: 3 - Alpha
Classifier: Environment :: Plugins
Classifier: Intended Audience :: System Administrators
Classifier: License :: OSI Approved :: Apache Software License
Classifier: Operating System :: POSIX :: Linux
Classifier: Programming Language :: Python
Classifier: Programming Language :: Python :: 2
Classifier: Programming Language :: Python :: 2.7
Classifier: Topic :: Internet :: WWW/HTTP
Classifier: Topic :: Security
Classifier: Topic :: System :: Installation/Setup
Classifier: Topic :: System :: Networking
Classifier: Topic :: System :: Systems Administration
Classifier: Topic :: Utilities
